[
  {
    "address": "native_token",
    "chainId": 10,
    "symbol": "ETH",
    "name": null,
    "decimals": 18,
    "logo": "https://raw.githubusercontent.com/celo-tracker/tokens/main/logos/ether.png",
    "coingeckoId": null,
    "usdPrice": "1843.79880141738849799717",
    "last24hrsPrice": null,
    "last7daysPrice": null,
    "tvl": null
  },
  {
    "address": "0x7F5c764cBc14f9669B88837ca1490cCa17c31607",
    "chainId": 10,
    "symbol": "USDC",
    "name": "USD Coin",
    "decimals": 6,
    "logo": "https://raw.githubusercontent.com/celo-tracker/tokens/main/logos/usdc.png",
    "coingeckoId": "usd-coin",
    "usdPrice": "1",
    "last24hrsPrice": null,
    "last7daysPrice": null,
    "tvl": "69714287.606253"
  },
  {
    "address": "0x8aE125E8653821E851F12A49F7765db9a9ce7384",
    "chainId": 10,
    "symbol": "DOLA",
    "name": "Dola USD Stablecoin",
    "decimals": 18,
    "logo": "https://ethereum-optimism.github.io/data/DOLA/logo.png",
    "coingeckoId": "dola-usd",
    "usdPrice": "0.99326601371738007505",
    "last24hrsPrice": null,
    "last7daysPrice": null,
    "tvl": "22844007.77035757051086925459214061916227945452"
  },
  {
    "address": "0x8c6f28f2F1A3C87F0f938b96d27520d9751ec8d9",
    "chainId": 10,
    "symbol": "sUSD",
    "name": "Synth sUSD",
    "decimals": 18,
    "logo": "https://ethereum-optimism.github.io/data/sUSD/logo.svg",
    "coingeckoId": "nusd",
    "usdPrice": "0.99960239645884878853",
    "last24hrsPrice": null,
    "last7daysPrice": null,
    "tvl": "15629208.7903560021274346136439442554641020592"
  },
  {
    "address": "0x340fE1D898ECCAad394e2ba0fC1F93d27c7b717A",
    "chainId": 10,
    "symbol": "wUSDR",
    "name": "Wrapped USDR",
    "decimals": 9,
    "logo": null,
    "unlisted": false,
    "coingeckoId": null,
    "usdPrice": "1.0528672505361658037",
    "last24hrsPrice": null,
    "last7daysPrice": null,
    "tvl": "5540390.72270531755560025389619711689"
  },
  {
    "address": "0x4200000000000000000000000000000000000006",
    "chainId": 10,
    "symbol": "WETH",
    "name": "Wrapped Ether",
    "decimals": 18,
    "logo": "https://ethereum-optimism.github.io/data/WETH/logo.png",
    "coingeckoId": "weth",
    "usdPrice": "1843.79880141738849799717",
    "last24hrsPrice": null,
    "last7daysPrice": null,
    "tvl": "31673952.06473694434838159565115750067794290179"
  },
  {
    "address": "0x9Bcef72be871e61ED4fBbc7630889beE758eb81D",
    "chainId": 10,
    "symbol": "rETH",
    "name": "Rocket Pool ETH",
    "decimals": 18,
    "logo": "https://ethereum-optimism.github.io/data/rETH/logo.png",
    "coingeckoId": "realms-of-ethernity",
    "usdPrice": "1977.65087410134476086699",
    "last24hrsPrice": null,
    "last7daysPrice": null,
    "tvl": "8938429.9067044897731328211510925556961677845"
  },
  {
    "address": "0x1F32b1c2345538c0c6f582fCB022739c4A194Ebb",
    "chainId": 10,
    "symbol": "wstETH",
    "name": "Wrapped liquid staked Ether 2.0",
    "decimals": 18,
    "logo": "https://ethereum-optimism.github.io/data/wstETH/logo.svg",
    "coingeckoId": "wrapped-steth",
    "usdPrice": "2075.59662748000577088677",
    "last24hrsPrice": null,
    "last7daysPrice": null,
    "tvl": "9612179.91874628755209409256792444587225116228"
  },
  {
    "address": "0x4200000000000000000000000000000000000042",
    "chainId": 10,
    "symbol": "OP",
    "name": "Optimism",
    "decimals": 18,
    "logo": "https://ethereum-optimism.github.io/data/OP/logo.png",
    "coingeckoId": "optimism",
    "usdPrice": "1.61513695171743927693",
    "last24hrsPrice": null,
    "last7daysPrice": null,
    "tvl": "8231277.56370802247478771369242850412219737808"
  },
  {
    "address": "0xc5b001DC33727F8F26880B184090D3E252470D45",
    "chainId": 10,
    "symbol": "ERN",
    "name": "Ethos Reserve Note",
    "decimals": 18,
    "logo": null,
    "unlisted": false,
    "coingeckoId": null,
    "usdPrice": "1.03175478773822172851",
    "last24hrsPrice": null,
    "last7daysPrice": null,
    "tvl": "1715726.641715694470844722253476345200625495"
  },
  {
    "address": "0xdFA46478F9e5EA86d57387849598dbFB2e964b02",
    "chainId": 10,
    "symbol": "MAI",
    "name": "Mai Stablecoin",
    "decimals": 18,
    "logo": "https://raw.githubusercontent.com/celo-tracker/tokens/main/logos/mai.png",
    "coingeckoId": null,
    "usdPrice": "0.99276618243137921243",
    "last24hrsPrice": null,
    "last7daysPrice": null,
    "tvl": "7923451.99540356968728420276174021946082765428"
  },
  {
    "address": "0xDA10009cBd5D07dd0CeCc66161FC93D7c9000da1",
    "chainId": 10,
    "symbol": "DAI",
    "name": "Dai Stablecoin",
    "decimals": 18,
    "logo": "https://raw.githubusercontent.com/celo-tracker/tokens/main/logos/dai.png",
    "coingeckoId": "dai",
    "usdPrice": "0.99995410396337504985",
    "last24hrsPrice": null,
    "last7daysPrice": null,
    "tvl": "5897044.42990409711681714662420188034386156452"
  },
  {
    "address": "0x6806411765Af15Bddd26f8f544A34cC40cb9838B",
    "chainId": 10,
    "symbol": "frxETH",
    "name": "Frax Ether",
    "decimals": 18,
    "logo": null,
    "unlisted": false,
    "coingeckoId": null,
    "usdPrice": "1844.72118171715963666491",
    "last24hrsPrice": null,
    "last7daysPrice": null,
    "tvl": "3924705.84501105214921133960644344173986915409"
  },
  {
    "address": "0xE405de8F52ba7559f9df3C368500B6E6ae6Cee49",
    "chainId": 10,
    "symbol": "sETH",
    "name": "Synth sETH",
    "decimals": 18,
    "logo": "https://ethereum-optimism.github.io/data/sETH/logo.svg",
    "coingeckoId": "seth",
    "usdPrice": "1839.48131817592159898002",
    "last24hrsPrice": null,
    "last7daysPrice": null,
    "tvl": "1830028.54656883795930767630403818109549360582"
  },
  {
    "address": "0x50c5725949A6F0c72E6C4a641F24049A917DB0Cb",
    "chainId": 10,
    "symbol": "LYRA",
    "name": "Lyra Token",
    "decimals": 18,
    "logo": "https://ethereum-optimism.github.io/data/LYRA/logo.png",
    "coingeckoId": "lyra-finance",
    "usdPrice": "0.0822240855779003417",
    "last24hrsPrice": null,
    "last7daysPrice": null,
    "tvl": "618356.08412106053025445377947605325214207482"
  },
  {
    "address": "0x2E3D870790dC77A83DD1d18184Acc7439A53f475",
    "chainId": 10,
    "symbol": "FRAX",
    "name": "Frax",
    "decimals": 18,
    "logo": "https://raw.githubusercontent.com/celo-tracker/tokens/main/logos/frax.png",
    "coingeckoId": null,
    "usdPrice": "0.99964660488691954865",
    "last24hrsPrice": null,
    "last7daysPrice": null,
    "tvl": "1421591.33577569546604144141078263474507647362"
  },
  {
    "address": "0xc40F949F8a4e094D1b49a23ea9241D289B7b2819",
    "chainId": 10,
    "symbol": "LUSD",
    "name": "LUSD Stablecoin",
    "decimals": 18,
    "logo": "https://ethereum-optimism.github.io/data/LUSD/logo.svg",
    "coingeckoId": "limited-usd",
    "usdPrice": "1.00726194867425281667",
    "last24hrsPrice": null,
    "last7daysPrice": null,
    "tvl": "2930519.87196728705452628657272714455898377348"
  },
  {
    "address": "0x3417E54A51924C225330f8770514aD5560B9098D",
    "chainId": 10,
    "symbol": "RED",
    "name": "REDKoin",
    "decimals": 18,
    "logo": null,
    "coingeckoId": null,
    "usdPrice": "3.5481238801386046502",
    "last24hrsPrice": null,
    "last7daysPrice": null,
    "tvl": "871573.61762751369147032705019066818502887852"
  },
  {
    "address": "0x3c8B650257cFb5f272f799F5e2b4e65093a11a05",
    "chainId": 10,
    "symbol": "VELO",
    "name": "Velodrome",
    "decimals": 18,
    "logo": "https://raw.githubusercontent.com/celo-tracker/tokens/main/logos/velo.webp",
    "coingeckoId": null,
    "usdPrice": "0.08061826794470158869",
    "last24hrsPrice": null,
    "last7daysPrice": null,
    "tvl": "4659934.61405630877614686096975710971538929851"
  },
  {
    "address": "0x217D47011b23BB961eB6D93cA9945B7501a5BB11",
    "chainId": 10,
    "symbol": "THALES",
    "name": "Thales DAO Token",
    "decimals": 18,
    "logo": "https://ethereum-optimism.github.io/data/THALES/logo.png",
    "coingeckoId": "thales",
    "usdPrice": "0.48680804461735889294",
    "last24hrsPrice": null,
    "last7daysPrice": null,
    "tvl": "722665.55908678703632491002384256418018503"
  },
  {
    "address": "0x5d47bAbA0d66083C52009271faF3F50DCc01023C",
    "chainId": 10,
    "symbol": "UNIDX",
    "name": "UniDex",
    "decimals": 18,
    "logo": null,
    "coingeckoId": null,
    "usdPrice": "4.28844918992737699501",
    "last24hrsPrice": null,
    "last7daysPrice": null,
    "tvl": "703237.70109335175297032933167949314006903156"
  },
  {
    "address": "0x74ccbe53F77b08632ce0CB91D3A545bF6B8E0979",
    "chainId": 10,
    "symbol": "fBOMB",
    "name": "Fantom Bomb",
    "decimals": 18,
    "logo": null,
    "unlisted": false,
    "coingeckoId": null,
    "usdPrice": "0.00570518266131160654",
    "last24hrsPrice": null,
    "last7daysPrice": null,
    "tvl": "571109.87444071028192097624934983000652054272"
  },
  {
    "address": "0x9485aca5bbBE1667AD97c7fE7C4531a624C8b1ED",
    "chainId": 10,
    "symbol": "agEUR",
    "name": "agEUR",
    "decimals": 18,
    "logo": "https://raw.githubusercontent.com/celo-tracker/tokens/main/logos/ageur.webp",
    "coingeckoId": null,
    "usdPrice": "1.07516846698594863677",
    "last24hrsPrice": null,
    "last7daysPrice": null,
    "tvl": "578908.92740270529870961711717173908435092208"
  },
  {
    "address": "0x46f21fDa29F1339e0aB543763FF683D399e393eC",
    "chainId": 10,
    "symbol": "opxveVELO",
    "name": "Perpetually Bonded Velo",
    "decimals": 18,
    "logo": null,
    "unlisted": false,
    "coingeckoId": null,
    "usdPrice": "0.06016055658066106556",
    "last24hrsPrice": null,
    "last7daysPrice": null,
    "tvl": "287935.4849267391206265192806754381988130016"
  },
  {
    "address": "0x39FdE572a18448F8139b7788099F0a0740f51205",
    "chainId": 10,
    "symbol": "OATH",
    "name": "Oath Token",
    "decimals": 18,
    "logo": null,
    "coingeckoId": null,
    "usdPrice": "0.08933882371760369409",
    "last24hrsPrice": null,
    "last7daysPrice": null,
    "tvl": "63140.57254527263632473598516501400417670815"
  },
  {
    "address": "0xCB8FA9a76b8e203D8C3797bF438d8FB81Ea3326A",
    "chainId": 10,
    "symbol": "alUSD",
    "name": "Alchemix USD",
    "decimals": 18,
    "logo": null,
    "coingeckoId": null,
    "usdPrice": "0.99618745612109435887",
    "last24hrsPrice": null,
    "last7daysPrice": null,
    "tvl": "1419844.24607346193157623578119016682395363597"
  },
  {
    "address": "0x3E29D3A9316dAB217754d13b28646B76607c5f04",
    "chainId": 10,
    "symbol": "alETH",
    "name": "Alchemix ETH",
    "decimals": 18,
    "logo": null,
    "coingeckoId": null,
    "usdPrice": "1832.06399768059619525598",
    "last24hrsPrice": null,
    "last7daysPrice": null,
    "tvl": "1677538.0812818779073904651671572137005277044"
  },
  {
    "address": "0x73cb180bf0521828d8849bc8CF2B920918e23032",
    "chainId": 10,
    "symbol": "USD+",
    "name": "USD+",
    "decimals": 6,
    "logo": "https://ethereum-optimism.github.io/data/USDplus/logo.svg",
    "coingeckoId": "usd",
    "usdPrice": "1.00087516717583435574",
    "last24hrsPrice": null,
    "last7daysPrice": null,
    "tvl": "5907156.23195562785029870138311945"
  },
  {
    "address": "0xdb4eA87fF83eB1c80b8976FC47731Da6a31D35e5",
    "chainId": 10,
    "symbol": "wTBT",
    "name": "wTBT(Bridge Token)",
    "decimals": 18,
    "logo": null,
    "unlisted": false,
    "coingeckoId": null,
    "usdPrice": "1.01886430579406837868",
    "last24hrsPrice": null,
    "last7daysPrice": null,
    "tvl": "2141948.60101950975602691001747999044203306328"
  },
  {
    "address": "0xbfD291DA8A403DAAF7e5E9DC1ec0aCEaCd4848B9",
    "chainId": 10,
    "symbol": "USX",
    "name": "dForce USD",
    "decimals": 18,
    "logo": "https://ethereum-optimism.github.io/data/USX/logo.svg",
    "coingeckoId": "token-dforce-usd",
    "usdPrice": "0.99999843156147687426",
    "last24hrsPrice": null,
    "last7daysPrice": null,
    "tvl": "1796818.3689599177989592866454543121433437913"
  },
  {
    "address": "0x970D50d09F3a656b43E11B0D45241a84e3a6e011",
    "chainId": 10,
    "symbol": "DAI+",
    "name": "DAI+",
    "decimals": 18,
    "logo": null,
    "unlisted": false,
    "coingeckoId": null,
    "usdPrice": "1.00103052169207333186",
    "last24hrsPrice": null,
    "last7daysPrice": null,
    "tvl": "1663564.9601857283306607606479975060467451568"
  },
  {
    "address": "0x920Cf626a271321C151D027030D5d08aF699456b",
    "chainId": 10,
    "symbol": "KWENTA",
    "name": "Kwenta",
    "decimals": 18,
    "logo": null,
    "unlisted": false,
    "coingeckoId": null,
    "usdPrice": "385.53855770147281748363",
    "last24hrsPrice": null,
    "last7daysPrice": null,
    "tvl": "1296067.16508488063430132725902537733425278888"
  },
  {
    "address": "0x94b008aA00579c1307B0EF2c499aD98a8ce58e58",
    "chainId": 10,
    "symbol": "USDT",
    "name": "Tether USD",
    "decimals": 6,
    "logo": "https://ethereum-optimism.github.io/data/USDT/logo.png",
    "coingeckoId": "tether",
    "usdPrice": "1.00050425414408862066",
    "last24hrsPrice": null,
    "last7daysPrice": null,
    "tvl": "1796793.41041484908392965758583376"
  },
  {
    "address": "0xB153FB3d196A8eB25522705560ac152eeEc57901",
    "chainId": 10,
    "symbol": "MIM",
    "name": "Magic Internet Money",
    "decimals": 18,
    "logo": "https://raw.githubusercontent.com/celo-tracker/tokens/main/logos/mim.png",
    "coingeckoId": null,
    "usdPrice": "0.99966615223517471703",
    "last24hrsPrice": null,
    "last7daysPrice": null,
    "tvl": "1603815.46452447519653478687293131930639442736"
  },
  {
    "address": "0x8700dAec35aF8Ff88c16BdF0418774CB3D7599B4",
    "chainId": 10,
    "symbol": "SNX",
    "name": "Synthetix Network Token",
    "decimals": 18,
    "logo": "https://ethereum-optimism.github.io/data/SNX/logo.svg",
    "coingeckoId": "havven",
    "usdPrice": "2.42330687779217616992",
    "last24hrsPrice": null,
    "last7daysPrice": null,
    "tvl": "616338.223989994997764350270769130947875432"
  },
  {
    "address": "0x4E720DD3Ac5CFe1e1fbDE4935f386Bb1C66F4642",
    "chainId": 10,
    "symbol": "BIFI",
    "name": "beefy.finance",
    "decimals": 18,
    "logo": "https://raw.githubusercontent.com/celo-tracker/tokens/main/logos/bifi.webp",
    "coingeckoId": null,
    "usdPrice": "431.65216386836668161913",
    "last24hrsPrice": null,
    "last7daysPrice": null,
    "tvl": "793673.89927087349807579973638573448784941048"
  },
  {
    "address": "0x1DB2466d9F5e10D7090E7152B68d62703a2245F0",
    "chainId": 10,
    "symbol": "SONNE",
    "name": "Sonne",
    "decimals": 18,
    "logo": "https://raw.githubusercontent.com/celo-tracker/tokens/main/logos/sonne.webp",
    "coingeckoId": null,
    "usdPrice": "0.08652952912445267156",
    "last24hrsPrice": null,
    "last7daysPrice": null,
    "tvl": "522702.7737929107578489427610207117875020645"
  },
  {
    "address": "0x484c2D6e3cDd945a8B2DF735e079178C1036578c",
    "chainId": 10,
    "symbol": "sfrxETH",
    "name": "Staked Frax Ether",
    "decimals": 18,
    "logo": null,
    "unlisted": false,
    "coingeckoId": null,
    "usdPrice": "1938.44526323058438607386",
    "last24hrsPrice": null,
    "last7daysPrice": null,
    "tvl": "555544.19958060302013263271664045019364917526"
  },
  {
    "address": "0x375488F097176507e39B9653b88FDc52cDE736Bf",
    "chainId": 10,
    "symbol": "TAROT",
    "name": "Tarot",
    "decimals": 18,
    "logo": "https://raw.githubusercontent.com/celo-tracker/tokens/main/logos/tarot.webp",
    "coingeckoId": null,
    "usdPrice": "0.08257017819770567884",
    "last24hrsPrice": null,
    "last7daysPrice": null,
    "tvl": "596968.36361157595190294388049334349301845196"
  },
  {
    "address": "0xFdb794692724153d1488CcdBE0C56c252596735F",
    "chainId": 10,
    "symbol": "LDO",
    "name": "Lido DAO Token",
    "decimals": 18,
    "logo": "https://ethereum-optimism.github.io/data/LDO/logo.svg",
    "coingeckoId": "lido-dao",
    "usdPrice": "1.97322021192473262027",
    "last24hrsPrice": null,
    "last7daysPrice": null,
    "tvl": "402137.30478042936807250919357724726556520872"
  },
  {
    "address": "0xAF9fE3B5cCDAe78188B1F8b9a49Da7ae9510F151",
    "chainId": 10,
    "symbol": "DHT",
    "name": "dHEDGE DAO Token",
    "decimals": 18,
    "logo": "https://ethereum-optimism.github.io/data/DHT/logo.svg",
    "unlisted": false,
    "coingeckoId": "dhedge-dao",
    "usdPrice": "0.13808075520949714482",
    "last24hrsPrice": null,
    "last7daysPrice": null,
    "tvl": "428547.7325246669234193130055911944154420439"
  },
  {
    "address": "0xB0B195aEFA3650A6908f15CdaC7D92F8a5791B0B",
    "chainId": 10,
    "symbol": "BOB",
    "name": "BOB",
    "decimals": 18,
    "logo": null,
    "coingeckoId": null,
    "usdPrice": "1.00037273171358250895",
    "last24hrsPrice": null,
    "last7daysPrice": null,
    "tvl": "695463.6650141469202009681109863095074124812"
  },
  {
    "address": "0x9e1028F5F1D5eDE59748FFceE5532509976840E0",
    "chainId": 10,
    "symbol": "PERP",
    "name": "Perpetual",
    "decimals": 18,
    "logo": "https://ethereum-optimism.github.io/data/PERP/logo.png",
    "coingeckoId": "perpetual-protocol",
    "usdPrice": "0.58153835133474608087",
    "last24hrsPrice": null,
    "last7daysPrice": null,
    "tvl": "362903.35093146573302464216931888058546510984"
  },
  {
    "address": "0x61BAADcF22d2565B0F471b291C475db5555e0b76",
    "chainId": 10,
    "symbol": "AELIN",
    "name": "Aelin Token",
    "decimals": 18,
    "logo": "https://ethereum-optimism.github.io/data/AELIN/logo.png",
    "coingeckoId": "aelin",
    "usdPrice": "938.83443424798664610153",
    "last24hrsPrice": null,
    "last7daysPrice": null,
    "tvl": "133954.89715554872828811033031122563403731936"
  },
  {
    "address": "0x7aE97042a4A0eB4D1eB370C34BfEC71042a056B7",
    "chainId": 10,
    "symbol": "UNLOCK",
    "name": "Unlock Token",
    "decimals": 18,
    "logo": null,
    "coingeckoId": null,
    "usdPrice": "0.01588225589909131891",
    "last24hrsPrice": null,
    "last7daysPrice": null,
    "tvl": "98386.32933574831084078243504439567157710772"
  },
  {
    "address": "0xc5102fE9359FD9a28f877a67E36B0F050d81a3CC",
    "chainId": 10,
    "symbol": "HOP",
    "name": "Hop",
    "decimals": 18,
    "logo": "https://raw.githubusercontent.com/celo-tracker/tokens/main/logos/hop.webp",
    "coingeckoId": null,
    "usdPrice": "0.0861154528899549333",
    "last24hrsPrice": null,
    "last7daysPrice": null,
    "tvl": "134104.4222223274239957353220189438190104239"
  },
  {
    "address": "0x7113370218f31764C1B6353BDF6004d86fF6B9cc",
    "chainId": 10,
    "symbol": "USDD",
    "name": "Decentralized USD",
    "decimals": 18,
    "logo": null,
    "unlisted": false,
    "coingeckoId": null,
    "usdPrice": "1.00042642578276913434",
    "last24hrsPrice": null,
    "last7daysPrice": null,
    "tvl": "59091.44339815162476813510657570081389484862"
  },
  {
    "address": "0xB0ae108669CEB86E9E98e8fE9e40d98b867855fD",
    "chainId": 10,
    "symbol": "RING",
    "name": "OneRing",
    "decimals": 18,
    "logo": null,
    "unlisted": false,
    "coingeckoId": null,
    "usdPrice": "0.01143704421094451819",
    "last24hrsPrice": null,
    "last7daysPrice": null,
    "tvl": "37140.3539675863404124332096484334172757134"
  },
  {
    "address": "0xfD389Dc9533717239856190F42475d3f263a270d",
    "chainId": 10,
    "symbol": "GRAIN",
    "name": "Granary Token",
    "decimals": 18,
    "logo": null,
    "unlisted": false,
    "coingeckoId": null,
    "usdPrice": "0.03519599895800747925",
    "last24hrsPrice": null,
    "last7daysPrice": null,
    "tvl": "10245.78732187479641471902976706569563559264"
  },
  {
    "address": "0x9e5AAC1Ba1a2e6aEd6b32689DFcF62A509Ca96f3",
    "chainId": 10,
    "symbol": "DF",
    "name": "dForce",
    "decimals": 18,
    "logo": "https://ethereum-optimism.github.io/data/DF/logo.svg",
    "unlisted": false,
    "coingeckoId": "dforce-token",
    "usdPrice": "0.0489657177572600158",
    "last24hrsPrice": null,
    "last7daysPrice": null,
    "tvl": "94420.88668766005144636607597307990561962505"
  },
  {
    "address": "0x10010078a54396F62c96dF8532dc2B4847d47ED3",
    "chainId": 10,
    "symbol": "HND",
    "name": "Hundred Finance",
    "decimals": 18,
    "logo": null,
    "coingeckoId": null,
    "usdPrice": "0.01548636364634650751",
    "last24hrsPrice": null,
    "last7daysPrice": null,
    "tvl": "49148.16502651325662279274335805445417503342"
  },
  {
    "address": "0x47536F17F4fF30e64A96a7555826b8f9e66ec468",
    "chainId": 10,
    "symbol": "MMY",
    "name": "MUMMY",
    "decimals": 18,
    "logo": null,
    "unlisted": false,
    "coingeckoId": null,
    "usdPrice": "2.34367923936388020804",
    "last24hrsPrice": null,
    "last7daysPrice": null,
    "tvl": "49185.07782930711243973495679165678556413964"
  },
  {
    "address": "0x6ca558bd3eaB53DA1B25aB97916dd14bf6CFEe4E",
    "chainId": 10,
    "symbol": "pETHo",
    "name": "pETHo",
    "decimals": 18,
    "logo": null,
    "coingeckoId": null,
    "usdPrice": "519.841420682559485402",
    "last24hrsPrice": null,
    "last7daysPrice": null,
    "tvl": "64359.55572508213308667743919171383812822389"
  },
  {
    "address": "0xc3864f98f2a61A7cAeb95b039D031b4E2f55e0e9",
    "chainId": 10,
    "symbol": "OpenX",
    "name": "OpenX Optimism",
    "decimals": 18,
    "logo": null,
    "coingeckoId": null,
    "usdPrice": "0.04254980008208949611",
    "last24hrsPrice": null,
    "last7daysPrice": null,
    "tvl": "57699.80169271640912414448642249352063521495"
  },
  {
    "address": "0xd652776dE7Ad802be5EC7beBfafdA37600222B48",
    "chainId": 10,
    "symbol": "SLM",
    "name": "SoliMax",
    "decimals": 18,
    "logo": null,
    "unlisted": false,
    "coingeckoId": null,
    "usdPrice": "0.0000816882419557031",
    "last24hrsPrice": null,
    "last7daysPrice": null,
    "tvl": "18566.1946399636498709017648158908314555236"
  },
  {
    "address": "0xa00E3A3511aAC35cA78530c85007AFCd31753819",
    "chainId": 10,
    "symbol": "KNC",
    "name": "Kyber Network Crystal v2",
    "decimals": 18,
    "logo": null,
    "unlisted": false,
    "coingeckoId": null,
    "usdPrice": "0.62469445255757248052",
    "last24hrsPrice": null,
    "last7daysPrice": null,
    "tvl": "42431.809148574287155132357166634964458365"
  },
  {
    "address": "0x15e770B95Edd73fD96b02EcE0266247D50895E76",
    "chainId": 10,
    "symbol": "JRT",
    "name": "Jarvis Reward Token",
    "decimals": 18,
    "logo": null,
    "unlisted": false,
    "coingeckoId": null,
    "usdPrice": "0.01019080419647446309",
    "last24hrsPrice": null,
    "last7daysPrice": null,
    "tvl": "38305.93833056042195092867714497589705829649"
  },
  {
    "address": "0x2513486f18eeE1498D7b6281f668B955181Dd0D9",
    "chainId": 10,
    "symbol": "xOpenX",
    "name": "OpenXSwap Gov Token",
    "decimals": 18,
    "logo": null,
    "coingeckoId": null,
    "usdPrice": "0.25586782359004840624",
    "last24hrsPrice": null,
    "last7daysPrice": null,
    "tvl": "22251.66434829428800439463499059472931246192"
  },
  {
    "address": "0xfDeFFc7Ad816BF7867C642dF7eBC2CC5554ec265",
    "chainId": 10,
    "symbol": "BeVELO",
    "name": "Beefy Velo",
    "decimals": 18,
    "logo": null,
    "unlisted": false,
    "coingeckoId": null,
    "usdPrice": "0.05153709830048947297",
    "last24hrsPrice": null,
    "last7daysPrice": null,
    "tvl": "23217.77454248905367423244482341414145897867"
  },
  {
    "address": "0x67CCEA5bb16181E7b4109c9c2143c24a1c2205Be",
    "chainId": 10,
    "symbol": "FXS",
    "name": "Frax Share",
    "decimals": 18,
    "logo": "https://raw.githubusercontent.com/celo-tracker/tokens/main/logos/fxs.webp",
    "coingeckoId": null,
    "usdPrice": "6.88433648290583230095",
    "last24hrsPrice": null,
    "last7daysPrice": null,
    "tvl": "18553.55315436788216880925864129393412197781"
  },
  {
    "address": "0x79AF5dd14e855823FA3E9ECAcdF001D99647d043",
    "chainId": 10,
    "symbol": "jEUR",
    "name": "Jarvis Synthetic Euro",
    "decimals": 18,
    "logo": null,
    "unlisted": false,
    "coingeckoId": null,
    "usdPrice": "1.07490485432129901456",
    "last24hrsPrice": null,
    "last7daysPrice": null,
    "tvl": "365053.68546019423612193783844005284793770515"
  },
  {
    "address": "0xFBc4198702E81aE77c06D58f81b629BDf36f0a71",
    "chainId": 10,
    "symbol": "sEUR",
    "name": "Synth sEUR",
    "decimals": 18,
    "logo": null,
    "unlisted": false,
    "coingeckoId": null,
    "usdPrice": "1.07352449797084605017",
    "last24hrsPrice": null,
    "last7daysPrice": null,
    "tvl": "315610.94733834630574850740323316779427324513"
  },
  {
    "address": "0xcB59a0A753fDB7491d5F3D794316F1adE197B21E",
    "chainId": 10,
    "symbol": "TUSD",
    "name": "TrueUSD",
    "decimals": 18,
    "logo": "https://ethereum-optimism.github.io/data/TUSD/logo.png",
    "coingeckoId": "true-usd",
    "usdPrice": "0.99006563575625356517",
    "last24hrsPrice": null,
    "last7daysPrice": null,
    "tvl": "16625.6542528965026665369609521647136290613"
  },
  {
    "address": "0x68f180fcCe6836688e9084f035309E29Bf0A2095",
    "chainId": 10,
    "symbol": "WBTC",
    "name": "Wrapped BTC",
    "decimals": 8,
    "logo": "https://ethereum-optimism.github.io/data/WBTC/logo.svg",
    "coingeckoId": "wrapped-bitcoin",
    "usdPrice": "28868.36027713625866050808",
    "last24hrsPrice": null,
    "last7daysPrice": null,
    "tvl": "11487.72502184678124089717546516"
  },
  {
    "address": "0x4D153F47F03c237F6360a6eccd185b4aE09c63D0",
    "chainId": 10,
    "symbol": "mooAaveOpDAI",
    "name": "Moo Aave Op DAI",
    "decimals": 18,
    "logo": null,
    "unlisted": false,
    "coingeckoId": null,
    "usdPrice": "1.01358292",
    "last24hrsPrice": null,
    "last7daysPrice": null,
    "tvl": null
  },
  {
    "address": "0x7eE71053102d54Fc843BaEBaf07277C2b6dB64f1",
    "chainId": 10,
    "symbol": "mooAaveOpETH",
    "name": "Moo Aave Op ETH",
    "decimals": 18,
    "logo": null,
    "unlisted": false,
    "coingeckoId": null,
    "usdPrice": "1884.38521547",
    "last24hrsPrice": null,
    "last7daysPrice": null,
    "tvl": null
  },
  {
    "address": "0x8e2cDf8c6477439B7C989e86B917D80871B92339",
    "chainId": 10,
    "symbol": "mooAaveOpWBTC",
    "name": "Moo Aave Op WBTC",
    "decimals": 18,
    "logo": null,
    "unlisted": false,
    "coingeckoId": null,
    "usdPrice": "274843537501200",
    "last24hrsPrice": null,
    "last7daysPrice": null,
    "tvl": null
  },
  {
    "address": "0xCa0E54b636DB823847B29F506BFFEE743F57729D",
    "chainId": 10,
    "symbol": "CHI",
    "name": "Chi USD",
    "decimals": 18,
    "logo": null,
    "unlisted": false,
    "coingeckoId": null,
    "usdPrice": "1.00088947848762320389",
    "last24hrsPrice": null,
    "last7daysPrice": null,
    "tvl": "1778165.14189348840694308463485453925991329028"
  },
  {
    "address": "0x929B939f8524c3Be977af57A4A0aD3fb1E374b50",
    "chainId": 10,
    "symbol": "MTA",
    "name": "Meta",
    "decimals": 18,
    "logo": null,
    "unlisted": false,
    "coingeckoId": null,
    "usdPrice": "0.03586282203947946722",
    "last24hrsPrice": null,
    "last7daysPrice": null,
    "tvl": "144168.60986093046524854342523677485025515384"
  },
  {
    "address": "0x296F55F8Fb28E498B858d0BcDA06D955B2Cb3f97",
    "chainId": 10,
    "symbol": "STG",
    "name": "StargateToken",
    "decimals": 18,
    "logo": null,
    "coingeckoId": null,
    "usdPrice": "0.66672791888484844296",
    "last24hrsPrice": null,
    "last7daysPrice": null,
    "tvl": "4286085.67660454904843012985490065224873055575"
  },
  {
    "address": "0xC26921B5b9ee80773774d36C84328ccb22c3a819",
    "chainId": 10,
    "symbol": "wOptiDoge",
    "name": "Wrapped OptiDoge",
    "decimals": 18,
    "logo": null,
    "unlisted": false,
    "coingeckoId": null,
    "usdPrice": "3.4154622560715e-7",
    "last24hrsPrice": null,
    "last7daysPrice": null,
    "tvl": "14515.18132341002309002552227310551189810228"
  },
  {
    "address": "0x12ff4a259e14D4DCd239C447D23C9b00F7781d8F",
    "chainId": 10,
    "symbol": "PEPE",
    "name": "PEPE Optimism",
    "decimals": 18,
    "logo": null,
    "unlisted": false,
    "coingeckoId": null,
    "usdPrice": "0.00008797276299532492",
    "last24hrsPrice": null,
    "last7daysPrice": null,
    "tvl": "10086.3549271777164357206643437425817262091"
  },
  {
    "address": "0x676f784d19c7F1Ac6C6BeaeaaC78B02a73427852",
    "chainId": 10,
    "symbol": "OPP",
    "name": "OptimismPrime",
    "decimals": 18,
    "logo": null,
    "coingeckoId": null,
    "usdPrice": "0.000090390301874281",
    "last24hrsPrice": null,
    "last7daysPrice": null,
    "tvl": "20390.25889782119409780864540860901168588387"
  },
  {
    "address": "0x6c2f7b6110a37b3B0fbdd811876be368df02E8B0",
    "chainId": 10,
    "symbol": "rETH",
    "name": "StaFi Staked ETH",
    "decimals": 18,
    "logo": null,
    "unlisted": false,
    "coingeckoId": null,
    "usdPrice": "1919.33448794110849929313",
    "last24hrsPrice": null,
    "last7daysPrice": null,
    "tvl": "265888.47710326882610677706828842552952657085"
  },
  {
    "address": "0xD8737CA46aa6285dE7B8777a8e3db232911baD41",
    "chainId": 10,
    "symbol": "FIS",
    "name": "StaFi Token",
    "decimals": 18,
    "logo": "https://ethereum-optimism.github.io/data/FIS/logo.svg",
    "unlisted": false,
    "coingeckoId": "stafi",
    "usdPrice": "0.42884692874801528598",
    "last24hrsPrice": null,
    "last7daysPrice": null,
    "tvl": "15223.72541294476161589136559864903422347647"
  },
  {
    "address": "0x00a35FD824c717879BF370E70AC6868b95870Dfb",
    "chainId": 10,
    "symbol": "IB",
    "name": "IronBank",
    "decimals": 18,
    "logo": null,
    "unlisted": false,
    "coingeckoId": null,
    "usdPrice": "1.27365499261216449269",
    "last24hrsPrice": null,
    "last7daysPrice": null,
    "tvl": "41628.38352863020927684475342858277601698959"
  },
  {
    "address": "0xa50B23cDfB2eC7c590e84f403256f67cE6dffB84",
    "chainId": 10,
    "symbol": "BLU",
    "name": "BLUE",
    "decimals": 18,
    "logo": null,
    "unlisted": false,
    "coingeckoId": null,
    "usdPrice": "0.00792710894032508654",
    "last24hrsPrice": null,
    "last7daysPrice": null,
    "tvl": "66383.5791665832916106183078322622231246753"
  },
  {
    "address": "0xcdB4bB51801A1F399d4402c61bC098a72c382E65",
    "chainId": 10,
    "symbol": "OPX",
    "name": "OPX",
    "decimals": 18,
    "logo": null,
    "coingeckoId": null,
    "usdPrice": "3.29626095512328722889",
    "last24hrsPrice": null,
    "last7daysPrice": null,
    "tvl": "59620.74225111598247379387083649180686403275"
  },
  {
    "address": "0x139283255069Ea5deeF6170699AAEF7139526f1f",
    "chainId": 10,
    "symbol": "OptiDoge",
    "name": "OptiDoge",
    "decimals": 18,
    "logo": null,
    "unlisted": false,
    "coingeckoId": null,
    "usdPrice": "8.1629236735884e-7",
    "last24hrsPrice": null,
    "last7daysPrice": null,
    "tvl": "14255.15796289338328404006719026145969988615"
  },
  {
    "address": "0xd52f94DF742a6F4B4C8b033369fE13A41782Bf44",
    "chainId": 10,
    "symbol": "L2DAO",
    "name": "Layer2DAO",
    "decimals": 18,
    "logo": null,
    "coingeckoId": null,
    "usdPrice": "0.00111756556499464537",
    "last24hrsPrice": null,
    "last7daysPrice": null,
    "tvl": "10662.38185158399380741678244074480092966384"
  },
  {
    "address": "0xF8e943f646816e4B51279B8934753821ED832Dca",
    "chainId": 10,
    "symbol": "CTH",
    "name": "Cthulhu",
    "decimals": 18,
    "logo": null,
    "unlisted": false,
    "coingeckoId": null,
    "usdPrice": "0.00022739129228411806",
    "last24hrsPrice": null,
    "last7daysPrice": null,
    "tvl": "53330.48524444486709562549665815778366575251"
  },
  {
    "address": "0xcfD1D50ce23C46D3Cf6407487B2F8934e96DC8f9",
    "chainId": 10,
    "symbol": "SPANK",
    "name": "SPANK",
    "decimals": 18,
    "logo": "https://ethereum-optimism.github.io/data/SPANK/logo.png",
    "coingeckoId": "spankchain",
    "usdPrice": "0.00771569128811125385",
    "last24hrsPrice": null,
    "last7daysPrice": null,
    "tvl": null
  },
  {
    "address": "0xE4F27b04cC7729901876B44f4EAA5102EC150265",
    "chainId": 10,
    "symbol": "XCHF",
    "name": "CryptoFranc",
    "decimals": 18,
    "logo": "https://ethereum-optimism.github.io/data/XCHF/logo.png",
    "coingeckoId": "cryptofranc",
    "usdPrice": "1.05924863714816733314",
    "last24hrsPrice": null,
    "last7daysPrice": null,
    "tvl": null
  },
  {
    "address": "0x0F5d45a7023612e9e244fe84FAc5fCf3740d1492",
    "chainId": 10,
    "symbol": "stkLYRA",
    "name": "Staked Lyra",
    "decimals": 18,
    "logo": "https://ethereum-optimism.github.io/data/stkLYRA/logo.svg",
    "unlisted": false,
    "coingeckoId": null,
    "usdPrice": "0.1671694238105209829",
    "last24hrsPrice": null,
    "last7daysPrice": null,
    "tvl": null
  },
  {
    "address": "0x8B21e9b7dAF2c4325bf3D18c1BeB79A347fE902A",
    "chainId": 10,
    "symbol": "COLLAB",
    "name": "Collab.Land",
    "decimals": 18,
    "logo": "https://ethereum-optimism.github.io/data/COLLAB/logo.png",
    "unlisted": false,
    "coingeckoId": "collab-land",
    "usdPrice": "0.03967255956719111332",
    "last24hrsPrice": null,
    "last7daysPrice": null,
    "tvl": null
  },
  {
    "address": "0xc96f4F893286137aC17e07Ae7F217fFca5db3AB6",
    "chainId": 10,
    "symbol": "NFTE",
    "name": "NFTEarth",
    "decimals": 18,
    "logo": null,
    "unlisted": false,
    "coingeckoId": null,
    "usdPrice": "0.08036434463476384037",
    "last24hrsPrice": null,
    "last7daysPrice": null,
    "tvl": null
  },
  {
    "address": "0xF98dCd95217E15E05d8638da4c91125E59590B07",
    "chainId": 10,
    "symbol": "KROM",
    "name": "Kromatika",
    "decimals": 18,
    "logo": "https://ethereum-optimism.github.io/data/KROM/logo.png",
    "coingeckoId": "kromatika",
    "usdPrice": "0.04975954698306835553",
    "last24hrsPrice": null,
    "last7daysPrice": null,
    "tvl": null
  },
  {
    "address": "0x76FB31fb4af56892A25e32cFC43De717950c9278",
    "chainId": 10,
    "symbol": "AAVE",
    "name": "Aave Token",
    "decimals": 18,
    "logo": "https://ethereum-optimism.github.io/data/AAVE/logo.svg",
    "coingeckoId": "aave",
    "usdPrice": "77.37786799778958307382",
    "last24hrsPrice": null,
    "last7daysPrice": null,
    "tvl": null
  },
  {
    "address": "0x374Ad0f47F4ca39c78E5Cc54f1C9e426FF8f231A",
    "chainId": 10,
    "symbol": "PREMIA",
    "name": "Premia",
    "decimals": 18,
    "logo": "https://ethereum-optimism.github.io/data/PREMIA/logo.svg",
    "coingeckoId": "premia",
    "usdPrice": "0.79188066594689464961",
    "last24hrsPrice": null,
    "last7daysPrice": null,
    "tvl": null
  },
  {
    "address": "0x50Bce64397C75488465253c0A034b8097FeA6578",
    "chainId": 10,
    "symbol": "HAN",
    "name": "HanChain",
    "decimals": 18,
    "logo": "https://ethereum-optimism.github.io/data/HAN/logo.svg",
    "coingeckoId": "hanchain",
    "usdPrice": "8.05287649193320741449",
    "last24hrsPrice": null,
    "last7daysPrice": null,
    "tvl": null
  },
  {
    "address": "0xe106e99472b2DEe098E5b8bBCD5d23331F346312",
    "chainId": 10,
    "symbol": "FUN",
    "name": "FunDex",
    "decimals": 18,
    "logo": null,
    "unlisted": false,
    "coingeckoId": null,
    "usdPrice": "0.05487146567022578563",
    "last24hrsPrice": null,
    "last7daysPrice": null,
    "tvl": null
  },
  {
    "address": "0x0994206dfE8De6Ec6920FF4D779B0d950605Fb53",
    "chainId": 10,
    "symbol": "CRV",
    "name": "Curve DAO Token",
    "decimals": 18,
    "logo": "https://ethereum-optimism.github.io/data/CRV/logo.png",
    "coingeckoId": "curve-dao-token",
    "usdPrice": "0.93456618999064996736",
    "last24hrsPrice": null,
    "last7daysPrice": null,
    "tvl": null
  },
  {
    "address": "0x6AF3cb766D6cd37449bfD321D961A61B0515c1BC",
    "chainId": 10,
    "symbol": "OS",
    "name": "Ethereans",
    "decimals": 18,
    "logo": null,
    "coingeckoId": null,
    "usdPrice": "4.79320188207367523735",
    "last24hrsPrice": null,
    "last7daysPrice": null,
    "tvl": null
  },
  {
    "address": "0x3e7eF8f50246f725885102E8238CBba33F276747",
    "chainId": 10,
    "symbol": "BOND",
    "name": "BarnBridge Governance Token (Optimism)",
    "decimals": 18,
    "logo": "https://ethereum-optimism.github.io/data/BOND/logo.svg",
    "coingeckoId": "barnbridge",
    "usdPrice": "3.83783381984783666317",
    "last24hrsPrice": null,
    "last7daysPrice": null,
    "tvl": null
  },
  {
    "address": "0x9C9e5fD8bbc25984B178FdCE6117Defa39d2db39",
    "chainId": 10,
    "symbol": "BUSD",
    "name": "BUSD Token",
    "decimals": 18,
    "logo": null,
    "unlisted": false,
    "coingeckoId": null,
    "usdPrice": "1.00009396586726861796",
    "last24hrsPrice": null,
    "last7daysPrice": null,
    "tvl": null
  },
  {
    "address": "0x09448876068907827ec15F49A8F1a58C70b04d45",
    "chainId": 10,
    "symbol": "sETHo",
    "name": "sETHo",
    "decimals": 18,
    "logo": null,
    "coingeckoId": null,
    "usdPrice": "0.29856976666450528372",
    "last24hrsPrice": "0.29856976666450528372",
    "last7daysPrice": null
  },
  {
    "address": "0x0Be27c140f9Bdad3474bEaFf0A413EC7e19e9B93",
    "chainId": 10,
    "symbol": "MNYe",
    "name": "Market Neutral Yield ETH Index",
    "decimals": 18,
    "logo": null,
    "coingeckoId": null,
    "usdPrice": "81.240450967689967651",
    "last24hrsPrice": "81.382675152141008507",
    "last7daysPrice": "85.373776074134153511"
  },
  {
    "address": "0x0d1a91354A387a1e9E8FCD8f576670c4C3b723cA",
    "chainId": 10,
    "symbol": "LyETHpt",
    "name": "Lyra ETH market Liquidity Pool Token",
    "decimals": 18,
    "logo": null,
    "coingeckoId": null,
    "usdPrice": null,
    "last24hrsPrice": null,
    "last7daysPrice": null
  },
  {
    "address": "0x117cFd9060525452db4A34d51c0b3b7599087f05",
    "chainId": 10,
    "symbol": "GYSR",
    "name": "Geyser",
    "decimals": 18,
    "logo": "https://ethereum-optimism.github.io/data/GYSR/logo.png",
    "coingeckoId": "geyser",
    "usdPrice": "0.063561040895663132",
    "last24hrsPrice": "0.057474135950265069",
    "last7daysPrice": "0.059669519537401598"
  },
  {
    "address": "0x350a791Bfc2C21F9Ed5d10980Dad2e2638ffa7f6",
    "chainId": 10,
    "symbol": "LINK",
    "name": "ChainLink Token",
    "decimals": 18,
    "logo": "https://ethereum-optimism.github.io/data/LINK/logo.png",
    "coingeckoId": "chainlink",
    "usdPrice": "6.115816174671737851",
    "last24hrsPrice": "6.916204712718448138",
    "last7daysPrice": "7.937350094255929747"
  },
  {
    "address": "0x5029C236320b8f15eF0a657054B84d90bfBEDED3",
    "chainId": 10,
    "symbol": "BitANT",
    "name": "BitANT",
    "decimals": 18,
    "logo": "https://ethereum-optimism.github.io/data/BitANT/logo.png",
    "coingeckoId": "bitant",
    "usdPrice": "0.000014424495708411",
    "last24hrsPrice": "0.000015500948206549",
    "last7daysPrice": "0.000018971954163866"
  },
  {
    "address": "0x65559aA14915a70190438eF90104769e5E890A00",
    "chainId": 10,
    "symbol": "ENS",
    "name": "Ethereum Name Service",
    "decimals": 18,
    "logo": "https://ethereum-optimism.github.io/data/ENS/logo.png",
    "coingeckoId": "ethereum-name-service",
    "usdPrice": "13.080210904189971142",
    "last24hrsPrice": "13.221855347066298152",
    "last7daysPrice": "16.888539019110539014"
  },
  {
    "address": "0x6F0fecBC276de8fC69257065fE47C5a03d986394",
    "chainId": 10,
    "symbol": "POP",
    "name": "Popcorn",
    "decimals": 18,
    "logo": "https://ethereum-optimism.github.io/data/POP/logo.svg",
    "coingeckoId": "pop-chest-token",
    "usdPrice": "0.38181439440694017",
    "last24hrsPrice": "0.351046476963646759",
    "last7daysPrice": null
  },
  {
    "address": "0x703D57164CA270b0B330A87FD159CfEF1490c0a5",
    "chainId": 10,
    "symbol": "WAD",
    "name": "WardenSwap",
    "decimals": 18,
    "logo": "https://ethereum-optimism.github.io/data/WAD/logo.png",
    "coingeckoId": "warden",
    "usdPrice": "0.02498581724832393663",
    "last24hrsPrice": "0.02498581724832393663",
    "last7daysPrice": "0.02294090094293929292"
  },
  {
    "address": "0x7FB688CCf682d58f86D7e38e03f9D22e7705448B",
    "chainId": 10,
    "symbol": "RAI",
    "name": "Rai Reflex Index",
    "decimals": 18,
    "logo": "https://ethereum-optimism.github.io/data/RAI/logo.svg",
    "coingeckoId": "rai",
    "usdPrice": "2.864862641340149727",
    "last24hrsPrice": "2.864862641340149727",
    "last7daysPrice": "2.864862641340149727"
  },
  {
    "address": "0x7b0bcC23851bBF7601efC9E9FE532Bf5284F65d3",
    "chainId": 10,
    "symbol": "EST",
    "name": "Erica Social Token",
    "decimals": 18,
    "logo": "https://ethereum-optimism.github.io/data/EST/logo.png",
    "coingeckoId": "erica-social-token",
    "usdPrice": "10.67556867945610772",
    "last24hrsPrice": "10.683980332288157826",
    "last7daysPrice": "10.684685658321347078"
  },
  {
    "address": "0xBD0D988376300D3a424bf10B8E8d1112A95b8326",
    "chainId": 10,
    "symbol": "oDOGE",
    "name": "Opti Doge",
    "decimals": 18,
    "logo": null,
    "coingeckoId": null,
    "usdPrice": "0",
    "last24hrsPrice": "0",
    "last7daysPrice": "0"
  },
  {
    "address": "0xCa98d642E158c3016E1c75dbcC3D5ECFe3E02A19",
    "chainId": 10,
    "symbol": "ETS V3 ARKS",
    "name": "ETS V3 Arrakis",
    "decimals": 6,
    "logo": null,
    "unlisted": false,
    "coingeckoId": null,
    "usdPrice": "0.999801173659775116",
    "last24hrsPrice": null,
    "last7daysPrice": null
  },
  {
    "address": "0xb20d84ebFeCdC6821448C7094564a039F0AE5EA4",
    "chainId": 10,
    "symbol": "FIRN",
    "name": "Firn Token",
    "decimals": 18,
    "logo": null,
    "coingeckoId": null,
    "usdPrice": "13.217321172974583341",
    "last24hrsPrice": "13.217321172974583341",
    "last7daysPrice": "13.217321172974583341"
  }
]